[
	{
		"InputData":
		{
			"Hierarchies":[["NancyCostCustomer2", "组织A", "园区A", "楼宇B"]],
			"Commodity":["$@Commodity_Electricity"],
			"DashboardInfo":[{
				"WigetName":"UNCarbonLine_1",
				"HierarchyName":["NancyCostCustomer2", "组织A", "园区B"],
				"IsCreateDashboard":"true",
				"DashboardName":"UNCarbon1012",
			},
			{
				"WigetName":"UNCarbonColumn_2",
				"HierarchyName":["NancyCostCustomer2", "组织A", "园区B"],
				"IsCreateDashboard":"false",
				"DashboardName":"UNCarbon1012",
			},
			{
				"WigetName":"UNCarbonPie_3",
				"HierarchyName":["NancyCostCustomer2", "组织A", "园区B"],
				"IsCreateDashboard":"false",
				"DashboardName":"UNCarbon1012",
			},
			{
				"WigetName":"UNCarbonDV_4",
				"HierarchyName":["NancyCostCustomer2", "组织A", "园区B"],
				"IsCreateDashboard":"false",
				"DashboardName":"UNCarbon1012",
			}],
			"Industry":"$@Zone_Extreme_Cold_Region_B$@Industry_Telecommunication_workshop",
		},
		"ExpectedData":
		{
			
		}
	}
]