[
	{
		"InputData":
		{
			"CommonName":"自定义能效标识1",
			"Commodity":"电",
			"KPIType":"单位人口",
			"LabellingLevel":"4级",
			"LabellingLevelValue":"4",
			"LabellingValue":[[{
				"LabellingLeftValue":"1",
			},
			{
				"LabellingLeftValue":"1",
				"LabellingRightValue":"2",
			},		
			{
				"LabellingLeftValue":"2",
				"LabellingRightValue":"3",
			},			
			{
				"LabellingLeftValue":"3",
				"LabellingRightValue":"4",
			},
			{
				"LabellingLeftValue":"4",
			}]]
		},
		"ExpectedData":
		{
			"CommonNames":["自定义能效标识1","必填项。"],
			"Commodity":"电",
			"KPIType":"单位人口",
			"LabellingLevel":"4级",
			"LabellingValue":[[{
				"LabellingLeftValue":"1",
			},
			{
				"LabellingLeftValue":"1",
				"LabellingRightValue":"2",
			},		
			{
				"LabellingLeftValue":"2",
				"LabellingRightValue":"3",
			},			
			{
				"LabellingLeftValue":"3",
				"LabellingRightValue":"4",
			},
			{
				"LabellingLeftValue":"4",
			}],
			[{
				"LabellingLeftValue":"必填项。",
				"LabellingRightValue":"必填项。",
			}]],
			"Order":["正序"],
			"Firstlabel":"<=",
			"Lastlabel":">",
			"UOM":"千瓦时/人",
		}
	}
]
